[
         {
                  "title": "These blood markers may higher risk of disease",
                  "description": "The price is something not defined as financial. It could be time.",
                  "author": "Alice Williams",
                  "time": "08 Mar 2023",
                  "img":"https://i.ibb.co/Lnt5ZD1/blog1.jpg"
         },
         {
                  "title": "Brushing your teeth may keep your heart healthy",
                  "description": "The price is something not defined as financial. It could be time.",
                  "author": "Alrado Deyam",
                  "time": "10 Mar 2023",
                  "img":"https://i.ibb.co/1qF70Rn/blog2.jpg"
         },
         {
                  "title": "Using anthrax to fight cancer effectively",
                  "description": "The price is something not necessarily defined as financial. It could be time, effort and sacrifice.",
                  "author": "Zenifer Suie",
                  "time": "02 Jan 2023",
                  "img":"https://i.ibb.co/C7KhQxx/blog3.jpg"
         }
]